rtfx/Constants.py
rtfx/Elements.py
rtfx/PropertySets.py
rtfx/Renderer.py
rtfx/Styles.py
rtfx/__init__.py
rtfx-0.1.dist-info/METADATA
rtfx-0.1.dist-info/WHEEL
rtfx-0.1.dist-info/top_level.txt
rtfx-0.1.dist-info/RECORD
